haxmas_day_9_Hasona57/__init__.py
haxmas_day_9_Hasona57/main.py
devboard_advent_calendar-0.1.0.dist-info/METADATA
devboard_advent_calendar-0.1.0.dist-info/WHEEL
devboard_advent_calendar-0.1.0.dist-info/entry_points.txt
devboard_advent_calendar-0.1.0.dist-info/RECORD
