Metadata-Version: 2.4
Name: devboard-advent-calendar
Version: 0.1.0
Summary: A terminal-based developer advent calendar built with Python and Textual
Author-email: Hassan Mohamed <hmmmma78@gmail.com>
License: MIT
Keywords: advent,calendar,developer,terminal,textual,tui
Classifier: Development Status :: 4 - Beta
Classifier: Intended Audience :: Developers
Classifier: License :: OSI Approved :: MIT License
Classifier: Programming Language :: Python :: 3
Classifier: Programming Language :: Python :: 3.8
Classifier: Programming Language :: Python :: 3.9
Classifier: Programming Language :: Python :: 3.10
Classifier: Programming Language :: Python :: 3.11
Classifier: Topic :: Software Development :: Libraries :: Python Modules
Requires-Python: >=3.8
Requires-Dist: textual
